setup.py
ugravatar/__init__.py
ugravatar/ugravatar.py
ugravatar.egg-info/PKG-INFO
ugravatar.egg-info/SOURCES.txt
ugravatar.egg-info/dependency_links.txt
ugravatar.egg-info/top_level.txt