Metadata-Version: 1.0
Name: ugravatar
Version: 0.0.2
Summary: Simple way to use Gravatar's service.
Home-page: https://bitbucket.org/umgeher/ugravatar/
Author: umgeher
Author-email: umgeher@mitgnu.com
License: http://changelog.umgeher.mitgnu.com/mitgnu/mitgnus-bsd-license/
Keywords: gravatar mitgnu
Platform: UNKNOWN
